{
  "item1": [
    {
      "src": "免税店_02.png"
    },
    {
      "src": "免税店_03.png"
    },
    {
      "src": "免税店_05.png"
    },
    {
      "src": "免税店_06.png"
    }
  ],
  "item2": [
    {
      "src": "item (1).jpg",
      "wen": "彩妆"
    },
    {
      "src": "item (2).jpg",
      "wen": "护肤"
    },
    {
      "src": "item (3).jpg",
      "wen": "轻奢"
    },
    {
      "src": "item (4).jpg",
      "wen": "母婴"
    }
  ],
  "item3": [
    {
      "src": "免税店_21.png",
      "wen": "伊思祛痘乳液,摆脱痘癌攻克换季痘难题,给痘痘穿上“塑身衣”轻松拥有蛋白肌",
      "span1": "59",
      "span2": "60人已购买",
      "img": "特卖_51.png"
    },
    {
      "src": "免税店_24.png",
      "wen": "【名媛大爱】日本RAFRA香橙泡沫洁面,奶油质地不伤肤,污垢轻松“揉”出来!",
      "span1": "118",
      "span2": "11人已购买",
      "img": "特卖_51.png"
    },
    {
      "src": "免税店_25.png",
      "wen": "【10片送5片】自然晨露水库炸弹面膜,水分直达肌底,给肌肤疯狂储水!",
      "huan": "满1元即可换购商品",
      "span1": "99",
      "span2": "18人已购买",
      "img": "特卖_51.png"
    }
  ],
  "item4": [
    {
      "src": "品牌 (2).jpg"
    },
    {
      "src": "品牌 (3).jpg"
    },
    {
      "src": "品牌 (1).jpg"
    },
    {
      "src": "品牌 (4).jpg"
    },
    {
      "src": "品牌 (5).jpg"
    },
    {
      "src": "品牌 (6).jpg"
    },
    {
      "src": "品牌 (7).jpg"
    },
    {
      "src": "品牌 (8).jpg"
    },
    {
      "src": "品牌 (12).jpg"
    },
    {
      "src": "品牌 (9).jpg"
    },
    {
      "src": "品牌 (10).jpg"
    },
    {
      "src": "品牌 (11).jpg"
    }
  ],
  "item5": [
    {
      "src": "lun (3).jpg",
      "wen": "伊思(It's skin)净化祛痘乳液",
      "jia": "¥59.9"
    },
    {
      "src": "lun (1).jpg",
      "wen": "RAFRA香橙碳酸泡沫洁面...",
      "jia": "¥118"
    },
    {
      "src": "lun (2).jpg",
      "wen": "芭妮兰至柔水润卸妆...",
      "jia": "¥109"
    }
  ],
  "item6": [
    {
      "src": "产品 (4).jpg",
      "wen": "伊思(It's skin)净化祛痘乳液",
      "jia": "¥59.9"
    },
    {
      "src": "产品 (5).jpg",
      "wen": "RAFRA香橙碳酸泡沫洁面...",
      "jia": "¥118"
    },
    {
      "src": "产品 (6).jpg",
      "wen": "芭妮兰至柔水润卸妆...",
      "jia": "¥109"
    }
  ],
  "aside1": [
    {
      "src": "图 (19).jpg"
    },
    {
      "src": "图 (19).jpg"
    }
  ],
  "tubiao": [
    {
      "src": "图 (15).jpg"
    },
    {
      "src": "图 (16).jpg"
    },
    {
      "src": "图 (17).jpg"
    },
    {
      "src": "图 (18).jpg"
    }
  ],
  "aside2": [
    {
      "src": "图 (2).jpg",
      "wen1": "5.1折",
      "wen2": "锁骨带它更迷人",
      "wen3": "施华洛世奇 渐变天鹅项链",
      "p": "今日特惠价:",
      "sp": "¥428",
      "del": "¥850",
      "div": "香港直邮"
    }
  ],
  "aside3": [
    {
      "src": "图 (8).jpg",
      "p": "Swarovski 施华洛世奇 链坠",
      "sp": "¥519",
      "del": "¥1100"
    },
    {
      "src": "图 (9).jpg",
      "p": "施华洛世奇 天使之吻水晶...",
      "sp": "¥398",
      "del": "¥980"
    },
    {
      "src": "图 (10).jpg",
      "p": "施华洛十字项链956722",
      "sp": "¥398",
      "del": "¥850"
    }
  ],
  "aside4": [
    {
      "src": "图 (12).jpg",
      "p": "卡西欧Casio男士腕...",
      "sp": "¥218",
      "del": "¥478"
    },
    {
      "src": "图 (13).jpg",
      "p": "卡西欧Casio男士腕...",
      "sp": "¥318",
      "del": "¥698"
    },
    {
      "src": "图 (14).jpg",
      "p": "卡西欧Casio男士腕...",
      "sp": "¥218",
      "del": "¥478"
    },
    {
      "src": "图 (13).jpg",
      "p": "卡西欧Casio男士腕...",
      "sp": "¥318",
      "del": "¥478"
    }
  ],
  "aside5": [
    {
      "src": "图 (22).jpg",
      "p": "【主播推荐款】众星专...",
      "sp": "¥1598",
      "del": "¥2500"
    },
    {
      "src": "图 (20).jpg",
      "p": "芙拉 女士牛皮芥末绿时尚...",
      "sp": "¥1589",
      "del": "¥2500"
    },
    {
      "src": "图 (21).jpg",
      "p": "芙拉 女士牛皮粉色时尚单...",
      "sp": "¥1599",
      "del": "¥2500"
    }
  ],
  "one": [
    {
      "src": "特卖_14.png",
      "wen": "分类"
    },
    {
      "src": "特卖_16.png",
      "wen": "签到"
    },
    {
      "src": "特卖_18.png",
      "wen": "凑团"
    },
    {
      "src": "特卖_20.png",
      "wen": "宝箱"
    }
  ],
  "two": [
    {
      "src": "特卖_36.png"
    },
    {
      "src": "特卖_37.png"
    },
    {
      "src": "特卖_38.png"
    },
    {
      "src": "特卖_39.png"
    },
    {
      "src": "特卖_41.png"
    },
    {
      "src": "特卖_42.png"
    },
    {
      "src": "特卖_43.png"
    }
  ],
  "fs1": [
    {
      "src": "服饰 (1).jpg"
    },
    {
      "src": "服饰 (10).jpg"
    }
  ],
  "fs2": [
    {
      "src": "服饰 (2).jpg",
      "sp1": "1折",
      "sp2": "单品包邮",
      "p1": "零束缚感无钢圈内衣",
      "p2": "维妮芳横拉丝无钢圈舒适聚拢文胸",
      "src1": "特卖_30.png",
      "sp3": "¥39",
      "del": "¥399"
    }
  ],
  "fs3": [
    {
      "src": "服饰 (6).jpg",
      "p1": "裳之梦夏季新品",
      "p2": "02天15时34分",
      "src1": "服饰 (11).jpg"
    },
    {
      "src": "服饰 (7).jpg",
      "p1": "简汐春夏潮品大汇集",
      "p2": "00天15时34分",
      "src1": "服饰 (12).jpg"
    },
    {
      "src": "服饰 (8).jpg",
      "p1": "亿瑞儿女装专场",
      "p2": "02天15时34分",
      "src1": "服饰 (13).jpg"
    },
    {
      "src": "服饰 (9).jpg",
      "p1": "春魅夏初 性感大促",
      "p2": "02天15时47分",
      "src1": "服饰 (14).jpg"
    },
    {
      "src": "服饰 (16).jpg",
      "p1": "四大男装联合团",
      "p2": "01天15时47分",
      "src1": "服饰 (15).jpg"
    }
  ],
  "my1": [
    {
      "src": "母婴 (1).jpg",
      "wen": "纸尿裤"
    },
    {
      "src": "母婴 (2).jpg",
      "wen": "奶粉"
    },
    {
      "src": "母婴 (3).jpg",
      "wen": "喂养用品"
    },
    {
      "src": "母婴 (4).jpg",
      "wen": "辅食"
    },
    {
      "src": "母婴 (5).jpg",
      "wen": "母婴洗护"
    },
    {
      "src": "母婴 (6).jpg",
      "wen": "孕妈风尚"
    },
    {
      "src": "母婴 (7).jpg",
      "wen": "童装童鞋"
    },
    {
      "src": "母婴 (8).jpg",
      "wen": "玩具"
    },
    {
      "src": "母婴 (9).jpg",
      "wen": "出行家居"
    },
    {
      "src": "母婴 (10).jpg",
      "wen": "凑团"
    }
  ],
  "my2": [
    {
      "src": "母婴 (12).jpg",
      "wen": "大王GOO.N男用拉拉裤L44",
      "span": "¥69",
      "del": "¥138"
    },
    {
      "src": "母婴 (13).jpg",
      "wen": "咕噜日记夏季新品咕噜猫短袖...",
      "span": "¥29",
      "del": "¥199"
    },
    {
      "src": "母婴 (14).jpg",
      "wen": "贝亲哺喂勺组DA39",
      "span": "¥28",
      "del": "¥38"
    }
  ],
  "my3": [
    {
      "src": "母婴 (15).jpg"
    },
    {
      "src": "母婴 (16).jpg"
    },
    {
      "src": "母婴 (17).jpg"
    },
    {
      "src": "母婴 (18).jpg"
    }
  ],
  "my4": [
    {
      "src": "母婴 (19).jpg"
    },
    {
      "src": "母婴 (20).jpg"
    },
    {
      "src": "母婴 (21).jpg"
    },
    {
      "src": "母婴 (22).jpg"
    }
  ],
  "my5": [
    {
      "src": "母婴 (24).jpg"
    },
    {
      "src": "母婴 (25).jpg"
    },
    {
      "src": "母婴 (26).jpg"
    },
    {
      "src": "母婴 (27).jpg"
    },
    {
      "src": "母婴 (28).jpg"
    },
    {
      "src": "母婴 (29).jpg"
    },
    {
      "src": "母婴 (30).jpg"
    },
    {
      "src": "母婴 (31).jpg"
    }
  ],
  "xb1": [
    {
      "src": "鞋包 (1).jpg"
    },
    {
      "src": "鞋包 (22).jpg"
    }
  ],
  "xb2": [
    {
      "src": "鞋包 (23).jpg",
      "sp1": "2.1折",
      "sp2": "单品包邮",
      "p1": "最美出游季 必备潮包",
      "p2": "北包包新款时尚印花链条单肩包",
      "src1": "特卖_30.png",
      "sp3": "¥49",
      "del": "¥229"
    }
  ],
  "xb3": [
    {
      "src": "鞋包 (5).jpg",
      "p1": "艾薇妮 爆款尖货感恩回馈",
      "p2": "01天15时33分",
      "src1": "鞋包 (6).jpg"
    },
    {
      "src": "鞋包 (7).jpg",
      "p1": "四大品牌联合特卖",
      "p2": "02天15时33分",
      "src1": "鞋包 (8).jpg"
    },
    {
      "src": "鞋包 (9).jpg",
      "p1": "北包包春时尚潮包",
      "p2": "01天15时33分",
      "src1": "鞋包 (10).jpg"
    },
    {
      "src": "鞋包 (11).jpg",
      "p1": "牛皮女鞋 狂欢一夏",
      "p2": "02天15时33分",
      "src1": "鞋包 (12).jpg"
    },
    {
      "src": "鞋包 (13).jpg",
      "p1": "娅莱娅换季大促销",
      "p2": "01天15时33分",
      "src1": "鞋包 (14).jpg"
    },
    {
      "src": "鞋包 (15).jpg",
      "p1": "真皮单鞋138元两双起",
      "p2": "02天15时33分",
      "src1": "鞋包 (16).jpg"
    },
    {
      "src": "鞋包 (17).jpg",
      "p1": "五一外出女鞋提前购",
      "p2": "01天15时33分",
      "src1": "鞋包 (18).jpg"
    },
    {
      "src": "鞋包 (24).jpg",
      "p1": "侨亿仕 春夏新品首发",
      "p2": "01天15时33分",
      "src1": "鞋包 (19).jpg"
    },
    {
      "src": "鞋包 (20).jpg",
      "p1": "NAIYEE春夏新品女鞋",
      "p2": "01天15时33分",
      "src1": "鞋包 (21).jpg"
    },
    {
      "src": "鞋包 (24).jpg",
      "p1": "艾薇妮 爆款尖货感恩回馈",
      "p2": "01天15时33分",
      "src1": "鞋包 (21).jpg"
    }
  ],
  "food1": [
    {
      "src": "食品 (1).jpg"
    },
    {
      "src": "食品 (1).jpg"
    }
  ],
  "food2": [
    {
      "src": "食品 (2).jpg",
      "wen": "饮品"
    },
    {
      "src": "食品 (3).jpg",
      "wen": "休闲零食"
    },
    {
      "src": "食品 (4).jpg",
      "wen": "瘦身"
    },
    {
      "src": "食品 (5).jpg",
      "wen": "保健"
    },
    {
      "src": "食品 (6).jpg",
      "wen": "营养早餐"
    }
  ],
  "food3": [
    {
      "src": "食品 (7).jpg",
      "wen": "FANCL HTC胶原蛋白饮品30日",
      "span": "¥449",
      "del": ""
    },
    {
      "src": "食品 (8).jpg",
      "wen": "POLA B.A抗糖化内服丸19.2g",
      "span": "¥499",
      "del": "¥999"
    },
    {
      "src": "食品 (9).jpg",
      "wen": "Nu-Lax乐康片 2盒装",
      "span": "¥95",
      "del": "¥229"
    }
  ],
  "food4": [
    {
      "src": "食品 (11).jpg"
    },
    {
      "src": "食品 (12).jpg"
    },
    {
      "src": "食品 (13).jpg"
    },
    {
      "src": "食品 (10).jpg"
    },
    {
      "src": "食品 (16).jpg"
    },
    {
      "src": "食品 (17).jpg"
    },
    {
      "src": "食品 (14).jpg"
    },
    {
      "src": "食品 (15).jpg"
    }
  ],
  "food5": [
    {
      "src": "食品 (19).jpg",
      "wen": "小老板海苔 香辣味4盒超值装",
      "span": "¥56",
      "del": "¥89"
    },
    {
      "src": "食品 (20).jpg",
      "wen": "The Market Grocer蔓越...",
      "span": "¥49",
      "del": "¥89"
    },
    {
      "src": "食品 (21).jpg",
      "wen": "澳洲        Tropicalfield...",
      "span": "¥69",
      "del": "¥119"
    }
  ],
  "food6": [
    {
      "src": "食品 (23).jpg",
      "wen": "Swisse胶原蛋白片100caps",
      "span": "¥118",
      "del": "¥269"
    },
    {
      "src": "食品 (24).jpg",
      "wen": "澳洲unichi玫瑰果精华胶囊6...",
      "span": "¥179",
      "del": "¥299"
    },
    {
      "src": "食品 (25).jpg",
      "wen": "whoo/后 明羲享亮白美肤",
      "span": "¥449",
      "del": "¥669"
    }
  ],
  "food7": [
    {
      "src": "食品 (27).jpg",
      "wen": "自然之宝液体钙软胶囊 12...",
      "span": "¥69",
      "del": "¥149"
    },
    {
      "src": "食品 (28).jpg",
      "wen": "复合维生素营养片(女)",
      "span": "¥139",
      "del": "¥189"
    },
    {
      "src": "食品 (29).jpg",
      "wen": "自然之宝润颜酵素胶囊",
      "span": "¥89",
      "del": "¥149"
    }
  ],
  "food8": [
    {
      "src": "食品 (31).jpg",
      "wen": "佰思蜜便携装野花蜜120g",
      "span": "¥128",
      "del": "¥168"
    },
    {
      "src": "食品 (32).jpg",
      "wen": "佰思蜜麦卢卡30+便携...",
      "span": "¥148",
      "del": "¥198"
    },
    {
      "src": "食品 (33).jpg",
      "wen": "新西兰进口佰思蜜三叶草...",
      "span": "¥178",
      "del": "¥208"
    }
  ],
  "food9": [
    {
      "src": "食品 (35).jpg",
      "wen": "熊孩子 榴莲干35g*3袋",
      "span": "¥32.5",
      "del": "¥75.8"
    },
    {
      "src": "食品 (36).jpg",
      "wen": "熊孩子 尝鲜酥脆组合322g",
      "span": "¥25.9",
      "del": "¥61.8"
    },
    {
      "src": "食品 (37).jpg",
      "wen": "熊孩子 蓝莓干110g",
      "span": "¥25.9",
      "del": "¥61.8"
    }
  ],
  "food10": [
    {
      "src": "食品 (39).jpg",
      "wen": "环球神秘美食手提礼盒",
      "span": "¥199",
      "del": "¥288"
    },
    {
      "src": "食品 (40).jpg",
      "wen": "泰国小老板脆海苔卷32.4g",
      "span": "¥27.8",
      "del": "¥68"
    },
    {
      "src": "食品 (41).jpg",
      "wen": "泰国养养冬荫功方便...",
      "span": "¥28.9",
      "del": "¥35"
    }
  ],
  "food11": [
    {
      "src": "食品 (43).jpg",
      "wen": "【冷链包邮】澳洲YP级牛...",
      "span": "¥44",
      "del": "¥89"
    },
    {
      "src": "食品 (44).jpg",
      "wen": "【冷链包邮】乌拉圭牛尾...",
      "span": "¥50",
      "del": "¥100"
    },
    {
      "src": "食品 (45).jpg",
      "wen": "【冷链包邮】澳洲S级牛腩...",
      "span": "¥39",
      "del": "¥78"
    }
  ]
}